MANIFEST.in
README.rst
setup.py
etunexus/__init__.py
etunexus/baseapp.py
etunexus/cas.py
etunexus/ei.py
etunexus/emc.py
etunexus/enum.py
etunexus/er.py
etunexus/logger.py
etunexus.egg-info/PKG-INFO
etunexus.egg-info/SOURCES.txt
etunexus.egg-info/dependency_links.txt
etunexus.egg-info/not-zip-safe
etunexus.egg-info/requires.txt
etunexus.egg-info/top_level.txt