Metadata-Version: 1.1
Name: etunexus
Version: 0.6.2
Summary: Etu Nexus API
Home-page: http://www.etunexus.com/
Author: Etu Corporation
Author-email: indichen@etusolution.com
License: GPL
Platform: UNKNOWN
Classifier: Development Status :: 2 - Pre-Alpha
Classifier: License :: OSI Approved :: GNU General Public License (GPL)
Classifier: Programming Language :: Python :: 2
Classifier: Programming Language :: Python :: 2.7
Classifier: Topic :: Software Development
Classifier: Topic :: Software Development :: Libraries
Classifier: Topic :: Software Development :: Libraries :: Python Modules
Classifier: Intended Audience :: Developers
